{
  "portraitScale": 1.0,
  "portraitTranslation": [
    0,
    0,
    0
  ],
  "profileScale": 1.0,
  "profileTranslation": [
    0,
    0,
    0
  ],
  "rootBone": "totodile",
  "animations": {
    "cry": "q.bedrock_primary('totodile', 'cry', q.curve('one'))"
  },
  "poses": {
    "standing": {
      "poseTypes": [
        "STAND",
        "NONE",
        "PORTRAIT",
        "PROFILE"
      ],
      "animations": [
        "q.bedrock('totodile', 'ground_idle')"
      ]
    },
    "walking": {
      "poseTypes": [
        "WALK"
      ],
      "animations": [
        "q.bedrock('totodile', 'ground_walk')"
      ]
    },
    "running": {
      "poseTypes": [
        "WALK"
      ],
      "animations": [
        "q.bedrock('totodile', 'ground_run')"
      ]
    },
    "battle-standing": {
      "poseTypes": [
        "STAND"
      ],
      "isBattle": true,
      "animations": [
        "q.bedrock('totodile', 'battle_idle')"
      ]
    },
    "sleep": {
      "poseTypes": [
        "SLEEP"
      ],
      "animations": [
        "q.bedrock('totodile', 'sleep')"
      ]
    },
    "float": {
      "poseTypes": [
        "FLOAT"
      ],
      "animations": [
        "q.bedrock('totodile', 'water_idle')"
      ]
    },
    "swim": {
      "poseTypes": [
        "SWIM"
      ],
      "animations": [
        "q.bedrock('totodile', 'water_swim')"
      ]
    },
    "surface-float": {
      "poseTypes": [
        "FLOAT"
      ],
      "animations": [
        "q.bedrock('totodile', 'water_idle')"
      ]
    },
    "surface-swim": {
      "poseTypes": [
        "SWIM"
      ],
      "animations": [
        "q.bedrock('totodile', 'water_swim')"
      ]
    }
  }
}