{"portraitScale":1.63,"portraitTranslation":[-0.88,3.42,0],"profileScale":0.42,"profileTranslation":[0.01,1.11,-5],"rootBone":"articuno","firstPersonCameraOffset":{"seat_1":[0,0.45,0]},"thirdPersonCameraOffset":{"seat_1":[0,0.5,1],"seat_1_reverse":[0,0.5,1]},"thirdPersonCameraOffsetNoViewBobbing":{"seat_1":[0,0.5,1],"seat_1_reverse":[0,0.5,1]},"animations":{},"poses":{"standing":{"poseName":"standing","poseTypes":["PORTRAIT","PROFILE","STAND","NONE"],"animations":["q.look('head_angle', 1, 1, 20, -90, 60, -37)","q.bedrock('articuno', 'ground_idle')"],"transformedParts":[{"part":"wing_open_left","isVisible":false},{"part":"wing_open_right","isVisible":false},{"part":"wing_closed_left","isVisible":true},{"part":"wing_closed_right","isVisible":true}],"quirks":["q.bedrock_quirk('articuno', 'blink')"]},"walk":{"poseName":"walk","poseTypes":["WALK"],"animations":["q.look('head_angle', 1, 1, 20, -90, 60, -37)","q.bedrock('articuno', 'ground_idle')","q.biped_walk(1, 1, 'leg_left', 'leg_right')"],"transformedParts":[{"part":"wing_open_left","isVisible":false},{"part":"wing_open_right","isVisible":false},{"part":"wing_closed_left","isVisible":true},{"part":"wing_closed_right","isVisible":true}],"quirks":["q.bedrock_quirk('articuno', 'blink')"]},"hover":{"poseName":"hover","poseTypes":["HOVER","FLOAT"],"animations":["q.pitch_tilt('body')","q.look('head_angle', 1, 1, 20, -90, 60, -37)","q.bedrock('articuno', 'air_idle')","q.sine_wing_flap(1, 1, 0.5, 'z', 'wing_open_left', 'wing_open_right')"],"transformedParts":[{"part":"wing_open_left","isVisible":true},{"part":"wing_open_right","isVisible":true},{"part":"wing_closed_left","isVisible":true},{"part":"wing_closed_right","isVisible":true}],"quirks":["q.bedrock_quirk('articuno', 'blink')"]},"fly":{"poseName":"fly","poseTypes":["FLY","SWIM"],"animations":["q.pitch_tilt('body')","q.look('head_angle', 1, 1, 20, -90, 60, -37)","q.bedrock('articuno', 'air_fly')"],"transformedParts":[{"part":"wing_open_left","isVisible":true},{"part":"wing_open_right","isVisible":true},{"part":"wing_closed_left","isVisible":true},{"part":"wing_closed_right","isVisible":true}],"quirks":["q.bedrock_quirk('articuno', 'blink')"]}}}