{
  "species": "cobblemon:houndoom",
  "order": 0,
  "variations": [
    {
      "aspects": [],
      "poser": "cobblemon:houndoom",
      "model": "cobblemon:houndoom_male.geo",
      "texture": "cobblemon:textures/pokemon/0229_houndoom/houndoom.png",
      "layers": []
    },
    {
      "aspects": [
        "shiny"
      ],
      "texture": "cobblemon:textures/pokemon/0229_houndoom/houndoom_shiny.png"
    },
    {
      "aspects": [
        "female"
      ],
      "model": "cobblemon:houndoom_female.geo"
    }
  ]
}