{
  "portraitScale": 1.0,
  "portraitTranslation": [
    0,
    0,
    0
  ],
  "profileScale": 1.0,
  "profileTranslation": [
    0,
    0,
    0
  ],
  "rootBone": "gligar",
  "animations": {
    "cry": "q.bedrock_primary('gligar', 'cry', q.curve('one'))"
  },
  "poses": {
    "standing": {
      "poseTypes": [
        "STAND",
        "NONE",
        "PORTRAIT",
        "PROFILE"
      ],
      "animations": [
        "q.bedrock('gligar', 'ground_idle')"
      ]
    },
    "battle-standing": {
      "poseTypes": [
        "STAND"
      ],
      "isBattle": true,
      "animations": [
        "q.bedrock('gligar', 'battle_idle')"
      ]
    }
  }
}